{"data":{"projectName":"","nodes":[{"name":"root","type":"Folder","attributes":{},"children":[{"name":"apps","type":"Folder","attributes":{},"link":"","children":[{"name":"web","type":"Folder","attributes":{},"link":"","children":[{"name":"src","type":"Folder","attributes":{},"link":"","children":[{"name":"app","type":"Folder","attributes":{},"link":"","children":[{"name":"layout.tsx","type":"File","attributes":{"loc":22.0,"indentation_level_0+":20.0,"indentation_level_1+":12.0,"indentation_level_2+":8.0,"indentation_level_3+":6.0,"indentation_level_4+":4.0,"indentation_level_5+":2.0,"indentation_level_6+":0.0,"indentation_level_7+":0.0,"indentation_level_8+":0.0,"indentation_level_9+":0.0,"indentation_level_10+":0.0},"link":"","children":[],"checksum":"66704e8afcc53930"},{"name":"(auth)","type":"Folder","attributes":{},"link":"","children":[{"name":"auth","type":"Folder","attributes":{},"link":"","children":[{"name":"login","type":"Folder","attributes":{},"link":"","children":[{"name":"page.tsx","type":"File","attributes":{"loc":97.0,"indentation_level_0+":85.0,"indentation_level_1+":75.0,"indentation_level_2+":67.0,"indentation_level_3+":53.0,"indentation_level_4+":43.0,"indentation_level_5+":38.0,"indentation_level_6+":27.0,"indentation_level_7+":14.0,"indentation_level_8+":0.0,"indentation_level_9+":0.0,"indentation_level_10+":0.0},"link":"","children":[],"checksum":"13877c9c149e865a"}]},{"name":"register","type":"Folder","attributes":{},"link":"","children":[{"name":"page.tsx","type":"File","attributes":{"loc":109.0,"indentation_level_0+":96.0,"indentation_level_1+":86.0,"indentation_level_2+":78.0,"indentation_level_3+":63.0,"indentation_level_4+":50.0,"indentation_level_5+":45.0,"indentation_level_6+":33.0,"indentation_level_7+":19.0,"indentation_level_8+":0.0,"indentation_level_9+":0.0,"indentation_level_10+":0.0},"link":"","children":[],"checksum":"a5ccfeb75a6f43de"}]}]}]},{"name":"(dashboard)","type":"Folder","attributes":{},"link":"","children":[{"name":"marketplace","type":"Folder","attributes":{},"link":"","children":[{"name":"[id]","type":"Folder","attributes":{},"link":"","children":[{"name":"page.tsx","type":"File","attributes":{"loc":77.0,"indentation_level_0+":66.0,"indentation_level_1+":57.0,"indentation_level_2+":46.0,"indentation_level_3+":34.0,"indentation_level_4+":26.0,"indentation_level_5+":13.0,"indentation_level_6+":3.0,"indentation_level_7+":1.0,"indentation_level_8+":0.0,"indentation_level_9+":0.0,"indentation_level_10+":0.0},"link":"","children":[],"checksum":"851892f8121fdce5"}]},{"name":"page.tsx","type":"File","attributes":{"loc":43.0,"indentation_level_0+":38.0,"indentation_level_1+":32.0,"indentation_level_2+":25.0,"indentation_level_3+":21.0,"indentation_level_4+":14.0,"indentation_level_5+":8.0,"indentation_level_6+":2.0,"indentation_level_7+":0.0,"indentation_level_8+":0.0,"indentation_level_9+":0.0,"indentation_level_10+":0.0},"link":"","children":[],"checksum":"dcb7b502ce254f89"}]},{"name":"admin","type":"Folder","attributes":{},"link":"","children":[{"name":"page.tsx","type":"File","attributes":{"loc":103.0,"indentation_level_0+":95.0,"indentation_level_1+":89.0,"indentation_level_2+":78.0,"indentation_level_3+":70.0,"indentation_level_4+":54.0,"indentation_level_5+":49.0,"indentation_level_6+":47.0,"indentation_level_7+":43.0,"indentation_level_8+":39.0,"indentation_level_9+":33.0,"indentation_level_10+":27.0},"link":"","children":[],"checksum":"854d14b78b6d43b9"}]},{"name":"market-data","type":"Folder","attributes":{},"link":"","children":[{"name":"page.tsx","type":"File","attributes":{"loc":282.0,"indentation_level_0+":254.0,"indentation_level_1+":234.0,"indentation_level_2+":188.0,"indentation_level_3+":161.0,"indentation_level_4+":135.0,"indentation_level_5+":109.0,"indentation_level_6+":71.0,"indentation_level_7+":38.0,"indentation_level_8+":9.0,"indentation_level_9+":4.0,"indentation_level_10+":0.0},"link":"","children":[],"checksum":"1519b09a298df0c6"}]},{"name":"my-blueprints","type":"Folder","attributes":{},"link":"","children":[{"name":"page.tsx","type":"File","attributes":{"loc":918.0,"indentation_level_0+":832.0,"indentation_level_1+":807.0,"indentation_level_2+":691.0,"indentation_level_3+":553.0,"indentation_level_4+":433.0,"indentation_level_5+":384.0,"indentation_level_6+":333.0,"indentation_level_7+":254.0,"indentation_level_8+":103.0,"indentation_level_9+":52.0,"indentation_level_10+":38.0},"link":"","children":[],"checksum":"ad51bedcbd5793f2"}]},{"name":"api-keys","type":"Folder","attributes":{},"link":"","children":[{"name":"page.tsx","type":"File","attributes":{"loc":153.0,"indentation_level_0+":134.0,"indentation_level_1+":126.0,"indentation_level_2+":112.0,"indentation_level_3+":90.0,"indentation_level_4+":61.0,"indentation_level_5+":47.0,"indentation_level_6+":28.0,"indentation_level_7+":4.0,"indentation_level_8+":0.0,"indentation_level_9+":0.0,"indentation_level_10+":0.0},"link":"","children":[],"checksum":"87c8697c1c4ae669"}]},{"name":"subscriptions","type":"Folder","attributes":{},"link":"","children":[{"name":"page.tsx","type":"File","attributes":{"loc":229.0,"indentation_level_0+":212.0,"indentation_level_1+":199.0,"indentation_level_2+":178.0,"indentation_level_3+":164.0,"indentation_level_4+":144.0,"indentation_level_5+":129.0,"indentation_level_6+":117.0,"indentation_level_7+":109.0,"indentation_level_8+":104.0,"indentation_level_9+":99.0,"indentation_level_10+":95.0},"link":"","children":[],"checksum":"f6c3c07e398d0a72"}]}]},{"name":"page.tsx","type":"File","attributes":{"loc":27.0,"indentation_level_0+":26.0,"indentation_level_1+":23.0,"indentation_level_2+":21.0,"indentation_level_3+":19.0,"indentation_level_4+":14.0,"indentation_level_5+":6.0,"indentation_level_6+":0.0,"indentation_level_7+":0.0,"indentation_level_8+":0.0,"indentation_level_9+":0.0,"indentation_level_10+":0.0},"link":"","children":[],"checksum":"a32a903b56d6c789"}]},{"name":"components","type":"Folder","attributes":{},"link":"","children":[{"name":"market","type":"Folder","attributes":{},"link":"","children":[{"name":"InteractiveMarketChart.tsx","type":"File","attributes":{"loc":614.0,"indentation_level_0+":536.0,"indentation_level_1+":502.0,"indentation_level_2+":395.0,"indentation_level_3+":297.0,"indentation_level_4+":230.0,"indentation_level_5+":199.0,"indentation_level_6+":192.0,"indentation_level_7+":139.0,"indentation_level_8+":87.0,"indentation_level_9+":41.0,"indentation_level_10+":21.0},"link":"","children":[],"checksum":"d4025c3764958635"}]},{"name":"marketplace","type":"Folder","attributes":{},"link":"","children":[{"name":"BacktestPanel.tsx","type":"File","attributes":{"loc":264.0,"indentation_level_0+":241.0,"indentation_level_1+":221.0,"indentation_level_2+":188.0,"indentation_level_3+":170.0,"indentation_level_4+":141.0,"indentation_level_5+":113.0,"indentation_level_6+":79.0,"indentation_level_7+":40.0,"indentation_level_8+":21.0,"indentation_level_9+":14.0,"indentation_level_10+":10.0},"link":"","children":[],"checksum":"0ed65b0829ed6dac"},{"name":"SubscribeButton.tsx","type":"File","attributes":{"loc":68.0,"indentation_level_0+":58.0,"indentation_level_1+":48.0,"indentation_level_2+":39.0,"indentation_level_3+":25.0,"indentation_level_4+":7.0,"indentation_level_5+":0.0,"indentation_level_6+":0.0,"indentation_level_7+":0.0,"indentation_level_8+":0.0,"indentation_level_9+":0.0,"indentation_level_10+":0.0},"link":"","children":[],"checksum":"0c8d5880bc66faba"},{"name":"BacktestPreviewPanel.tsx","type":"File","attributes":{"loc":256.0,"indentation_level_0+":236.0,"indentation_level_1+":216.0,"indentation_level_2+":182.0,"indentation_level_3+":163.0,"indentation_level_4+":136.0,"indentation_level_5+":106.0,"indentation_level_6+":77.0,"indentation_level_7+":40.0,"indentation_level_8+":21.0,"indentation_level_9+":14.0,"indentation_level_10+":10.0},"link":"","children":[],"checksum":"66a9b7149f1242d4"},{"name":"BlueprintCard.tsx","type":"File","attributes":{"loc":53.0,"indentation_level_0+":46.0,"indentation_level_1+":40.0,"indentation_level_2+":34.0,"indentation_level_3+":26.0,"indentation_level_4+":15.0,"indentation_level_5+":4.0,"indentation_level_6+":1.0,"indentation_level_7+":0.0,"indentation_level_8+":0.0,"indentation_level_9+":0.0,"indentation_level_10+":0.0},"link":"","children":[],"checksum":"106f531a7669acc6"}]},{"name":"ui","type":"Folder","attributes":{},"link":"","children":[{"name":"NavBar.tsx","type":"File","attributes":{"loc":99.0,"indentation_level_0+":86.0,"indentation_level_1+":78.0,"indentation_level_2+":68.0,"indentation_level_3+":55.0,"indentation_level_4+":47.0,"indentation_level_5+":40.0,"indentation_level_6+":32.0,"indentation_level_7+":23.0,"indentation_level_8+":9.0,"indentation_level_9+":2.0,"indentation_level_10+":0.0},"link":"","children":[],"checksum":"374ec16ee44e3f4e"}]},{"name":"providers","type":"Folder","attributes":{},"link":"","children":[{"name":"SessionProvider.tsx","type":"File","attributes":{"loc":83.0,"indentation_level_0+":70.0,"indentation_level_1+":56.0,"indentation_level_2+":31.0,"indentation_level_3+":16.0,"indentation_level_4+":2.0,"indentation_level_5+":0.0,"indentation_level_6+":0.0,"indentation_level_7+":0.0,"indentation_level_8+":0.0,"indentation_level_9+":0.0,"indentation_level_10+":0.0},"link":"","children":[],"checksum":"b5b586b0dd33c988"}]}]},{"name":"lib","type":"Folder","attributes":{},"link":"","children":[{"name":"api-client","type":"Folder","attributes":{},"link":"","children":[{"name":"subscriptions.client.ts","type":"File","attributes":{"loc":24.0,"indentation_level_0+":19.0,"indentation_level_1+":14.0,"indentation_level_2+":5.0,"indentation_level_3+":0.0,"indentation_level_4+":0.0,"indentation_level_5+":0.0,"indentation_level_6+":0.0,"indentation_level_7+":0.0,"indentation_level_8+":0.0,"indentation_level_9+":0.0,"indentation_level_10+":0.0},"link":"","children":[],"checksum":"4eda2d6311f074be"},{"name":"trade-logs.client.ts","type":"File","attributes":{"loc":7.0,"indentation_level_0+":6.0,"indentation_level_1+":2.0,"indentation_level_2+":1.0,"indentation_level_3+":0.0,"indentation_level_4+":0.0,"indentation_level_5+":0.0,"indentation_level_6+":0.0,"indentation_level_7+":0.0,"indentation_level_8+":0.0,"indentation_level_9+":0.0,"indentation_level_10+":0.0},"link":"","children":[],"checksum":"abdacbb36cada1e6"},{"name":"base.ts","type":"File","attributes":{"loc":71.0,"indentation_level_0+":56.0,"indentation_level_1+":46.0,"indentation_level_2+":43.0,"indentation_level_3+":17.0,"indentation_level_4+":17.0,"indentation_level_5+":0.0,"indentation_level_6+":0.0,"indentation_level_7+":0.0,"indentation_level_8+":0.0,"indentation_level_9+":0.0,"indentation_level_10+":0.0},"link":"","children":[],"checksum":"6d5bfb76f360bf72"},{"name":"blueprints.client.ts","type":"File","attributes":{"loc":50.0,"indentation_level_0+":39.0,"indentation_level_1+":32.0,"indentation_level_2+":11.0,"indentation_level_3+":0.0,"indentation_level_4+":0.0,"indentation_level_5+":0.0,"indentation_level_6+":0.0,"indentation_level_7+":0.0,"indentation_level_8+":0.0,"indentation_level_9+":0.0,"indentation_level_10+":0.0},"link":"","children":[],"checksum":"bbeb4bcf867c9afe"},{"name":"auth.client.ts","type":"File","attributes":{"loc":24.0,"indentation_level_0+":19.0,"indentation_level_1+":12.0,"indentation_level_2+":8.0,"indentation_level_3+":0.0,"indentation_level_4+":0.0,"indentation_level_5+":0.0,"indentation_level_6+":0.0,"indentation_level_7+":0.0,"indentation_level_8+":0.0,"indentation_level_9+":0.0,"indentation_level_10+":0.0},"link":"","children":[],"checksum":"3571972742420747"},{"name":"api-keys.client.ts","type":"File","attributes":{"loc":15.0,"indentation_level_0+":12.0,"indentation_level_1+":7.0,"indentation_level_2+":1.0,"indentation_level_3+":0.0,"indentation_level_4+":0.0,"indentation_level_5+":0.0,"indentation_level_6+":0.0,"indentation_level_7+":0.0,"indentation_level_8+":0.0,"indentation_level_9+":0.0,"indentation_level_10+":0.0},"link":"","children":[],"checksum":"e450472cd6a833c0"},{"name":"market-data.client.ts","type":"File","attributes":{"loc":19.0,"indentation_level_0+":17.0,"indentation_level_1+":10.0,"indentation_level_2+":6.0,"indentation_level_3+":0.0,"indentation_level_4+":0.0,"indentation_level_5+":0.0,"indentation_level_6+":0.0,"indentation_level_7+":0.0,"indentation_level_8+":0.0,"indentation_level_9+":0.0,"indentation_level_10+":0.0},"link":"","children":[],"checksum":"b024f389ba280164"}]}]}]}]},{"name":"api","type":"Folder","attributes":{},"link":"","children":[{"name":"src","type":"Folder","attributes":{},"link":"","children":[{"name":"auth","type":"Folder","attributes":{},"link":"","children":[{"name":"roles.guard.ts","type":"File","attributes":{"loc":30.0,"indentation_level_0+":25.0,"indentation_level_1+":18.0,"indentation_level_2+":15.0,"indentation_level_3+":3.0,"indentation_level_4+":0.0,"indentation_level_5+":0.0,"indentation_level_6+":0.0,"indentation_level_7+":0.0,"indentation_level_8+":0.0,"indentation_level_9+":0.0,"indentation_level_10+":0.0},"link":"","children":[],"checksum":"f29c09308bda084e"},{"name":"auth.controller.ts","type":"File","attributes":{"loc":84.0,"indentation_level_0+":75.0,"indentation_level_1+":58.0,"indentation_level_2+":34.0,"indentation_level_3+":5.0,"indentation_level_4+":3.0,"indentation_level_5+":0.0,"indentation_level_6+":0.0,"indentation_level_7+":0.0,"indentation_level_8+":0.0,"indentation_level_9+":0.0,"indentation_level_10+":0.0},"link":"","children":[],"checksum":"089561db9784269f"},{"name":"auth.service.ts","type":"File","attributes":{"loc":54.0,"indentation_level_0+":46.0,"indentation_level_1+":36.0,"indentation_level_2+":28.0,"indentation_level_3+":8.0,"indentation_level_4+":0.0,"indentation_level_5+":0.0,"indentation_level_6+":0.0,"indentation_level_7+":0.0,"indentation_level_8+":0.0,"indentation_level_9+":0.0,"indentation_level_10+":0.0},"link":"","children":[],"checksum":"ef8bd60dfe31e3ee"},{"name":"jwt.strategy.ts","type":"File","attributes":{"loc":36.0,"indentation_level_0+":30.0,"indentation_level_1+":20.0,"indentation_level_2+":9.0,"indentation_level_3+":6.0,"indentation_level_4+":2.0,"indentation_level_5+":0.0,"indentation_level_6+":0.0,"indentation_level_7+":0.0,"indentation_level_8+":0.0,"indentation_level_9+":0.0,"indentation_level_10+":0.0},"link":"","children":[],"checksum":"9b6e0998241449da"},{"name":"auth.repository.ts","type":"File","attributes":{"loc":20.0,"indentation_level_0+":16.0,"indentation_level_1+":10.0,"indentation_level_2+":3.0,"indentation_level_3+":0.0,"indentation_level_4+":0.0,"indentation_level_5+":0.0,"indentation_level_6+":0.0,"indentation_level_7+":0.0,"indentation_level_8+":0.0,"indentation_level_9+":0.0,"indentation_level_10+":0.0},"link":"","children":[],"checksum":"53e43e664ba32787"},{"name":"jwt-auth.guard.ts","type":"File","attributes":{"loc":5.0,"indentation_level_0+":4.0,"indentation_level_1+":0.0,"indentation_level_2+":0.0,"indentation_level_3+":0.0,"indentation_level_4+":0.0,"indentation_level_5+":0.0,"indentation_level_6+":0.0,"indentation_level_7+":0.0,"indentation_level_8+":0.0,"indentation_level_9+":0.0,"indentation_level_10+":0.0},"link":"","children":[],"checksum":"a29525b331670b33"},{"name":"roles.decorator.ts","type":"File","attributes":{"loc":4.0,"indentation_level_0+":3.0,"indentation_level_1+":0.0,"indentation_level_2+":0.0,"indentation_level_3+":0.0,"indentation_level_4+":0.0,"indentation_level_5+":0.0,"indentation_level_6+":0.0,"indentation_level_7+":0.0,"indentation_level_8+":0.0,"indentation_level_9+":0.0,"indentation_level_10+":0.0},"link":"","children":[],"checksum":"2b0bef03269deb3f"},{"name":"auth.module.ts","type":"File","attributes":{"loc":21.0,"indentation_level_0+":20.0,"indentation_level_1+":10.0,"indentation_level_2+":5.0,"indentation_level_3+":2.0,"indentation_level_4+":0.0,"indentation_level_5+":0.0,"indentation_level_6+":0.0,"indentation_level_7+":0.0,"indentation_level_8+":0.0,"indentation_level_9+":0.0,"indentation_level_10+":0.0},"link":"","children":[],"checksum":"2f59c9baf4804062"}]},{"name":"market-data","type":"Folder","attributes":{},"link":"","children":[{"name":"market-data.controller.ts","type":"File","attributes":{"loc":18.0,"indentation_level_0+":16.0,"indentation_level_1+":8.0,"indentation_level_2+":3.0,"indentation_level_3+":0.0,"indentation_level_4+":0.0,"indentation_level_5+":0.0,"indentation_level_6+":0.0,"indentation_level_7+":0.0,"indentation_level_8+":0.0,"indentation_level_9+":0.0,"indentation_level_10+":0.0},"link":"","children":[],"checksum":"fe3cf62618820d15"},{"name":"market-data.service.ts","type":"File","attributes":{"loc":11.0,"indentation_level_0+":9.0,"indentation_level_1+":4.0,"indentation_level_2+":1.0,"indentation_level_3+":0.0,"indentation_level_4+":0.0,"indentation_level_5+":0.0,"indentation_level_6+":0.0,"indentation_level_7+":0.0,"indentation_level_8+":0.0,"indentation_level_9+":0.0,"indentation_level_10+":0.0},"link":"","children":[],"checksum":"c258070db0bb1a5b"},{"name":"market-data.module.ts","type":"File","attributes":{"loc":11.0,"indentation_level_0+":10.0,"indentation_level_1+":3.0,"indentation_level_2+":0.0,"indentation_level_3+":0.0,"indentation_level_4+":0.0,"indentation_level_5+":0.0,"indentation_level_6+":0.0,"indentation_level_7+":0.0,"indentation_level_8+":0.0,"indentation_level_9+":0.0,"indentation_level_10+":0.0},"link":"","children":[],"checksum":"05c31c545e8ce63e"}]},{"name":"prisma","type":"Folder","attributes":{},"link":"","children":[{"name":"prisma.service.ts","type":"File","attributes":{"loc":9.0,"indentation_level_0+":8.0,"indentation_level_1+":3.0,"indentation_level_2+":1.0,"indentation_level_3+":0.0,"indentation_level_4+":0.0,"indentation_level_5+":0.0,"indentation_level_6+":0.0,"indentation_level_7+":0.0,"indentation_level_8+":0.0,"indentation_level_9+":0.0,"indentation_level_10+":0.0},"link":"","children":[],"checksum":"d77305b7ba76cf5b"},{"name":"prisma.module.ts","type":"File","attributes":{"loc":9.0,"indentation_level_0+":8.0,"indentation_level_1+":2.0,"indentation_level_2+":0.0,"indentation_level_3+":0.0,"indentation_level_4+":0.0,"indentation_level_5+":0.0,"indentation_level_6+":0.0,"indentation_level_7+":0.0,"indentation_level_8+":0.0,"indentation_level_9+":0.0,"indentation_level_10+":0.0},"link":"","children":[],"checksum":"c1d5cdfe83f9323f"}]},{"name":"positions","type":"Folder","attributes":{},"link":"","children":[{"name":"positions.service.ts","type":"File","attributes":{"loc":22.0,"indentation_level_0+":19.0,"indentation_level_1+":12.0,"indentation_level_2+":8.0,"indentation_level_3+":0.0,"indentation_level_4+":0.0,"indentation_level_5+":0.0,"indentation_level_6+":0.0,"indentation_level_7+":0.0,"indentation_level_8+":0.0,"indentation_level_9+":0.0,"indentation_level_10+":0.0},"link":"","children":[],"checksum":"5412e425ac9f8d73"},{"name":"positions.controller.ts","type":"File","attributes":{"loc":19.0,"indentation_level_0+":17.0,"indentation_level_1+":5.0,"indentation_level_2+":1.0,"indentation_level_3+":0.0,"indentation_level_4+":0.0,"indentation_level_5+":0.0,"indentation_level_6+":0.0,"indentation_level_7+":0.0,"indentation_level_8+":0.0,"indentation_level_9+":0.0,"indentation_level_10+":0.0},"link":"","children":[],"checksum":"c397ba73bbc5e766"},{"name":"positions.module.ts","type":"File","attributes":{"loc":13.0,"indentation_level_0+":12.0,"indentation_level_1+":3.0,"indentation_level_2+":0.0,"indentation_level_3+":0.0,"indentation_level_4+":0.0,"indentation_level_5+":0.0,"indentation_level_6+":0.0,"indentation_level_7+":0.0,"indentation_level_8+":0.0,"indentation_level_9+":0.0,"indentation_level_10+":0.0},"link":"","children":[],"checksum":"a5c26151e1e0f127"}]},{"name":"heartbeat","type":"Folder","attributes":{},"link":"","children":[{"name":"heartbeat.module.ts","type":"File","attributes":{"loc":14.0,"indentation_level_0+":13.0,"indentation_level_1+":3.0,"indentation_level_2+":0.0,"indentation_level_3+":0.0,"indentation_level_4+":0.0,"indentation_level_5+":0.0,"indentation_level_6+":0.0,"indentation_level_7+":0.0,"indentation_level_8+":0.0,"indentation_level_9+":0.0,"indentation_level_10+":0.0},"link":"","children":[],"checksum":"8b824d0f359f5ced"},{"name":"heartbeat.service.ts","type":"File","attributes":{"loc":248.0,"indentation_level_0+":216.0,"indentation_level_1+":203.0,"indentation_level_2+":169.0,"indentation_level_3+":121.0,"indentation_level_4+":59.0,"indentation_level_5+":17.0,"indentation_level_6+":0.0,"indentation_level_7+":0.0,"indentation_level_8+":0.0,"indentation_level_9+":0.0,"indentation_level_10+":0.0},"link":"","children":[],"checksum":"77944c1346806f3f"},{"name":"heartbeat.controller.ts","type":"File","attributes":{"loc":18.0,"indentation_level_0+":16.0,"indentation_level_1+":5.0,"indentation_level_2+":1.0,"indentation_level_3+":0.0,"indentation_level_4+":0.0,"indentation_level_5+":0.0,"indentation_level_6+":0.0,"indentation_level_7+":0.0,"indentation_level_8+":0.0,"indentation_level_9+":0.0,"indentation_level_10+":0.0},"link":"","children":[],"checksum":"40821401555a17f1"}]},{"name":"trading","type":"Folder","attributes":{},"link":"","children":[{"name":"trading.module.ts","type":"File","attributes":{"loc":13.0,"indentation_level_0+":12.0,"indentation_level_1+":7.0,"indentation_level_2+":4.0,"indentation_level_3+":2.0,"indentation_level_4+":0.0,"indentation_level_5+":0.0,"indentation_level_6+":0.0,"indentation_level_7+":0.0,"indentation_level_8+":0.0,"indentation_level_9+":0.0,"indentation_level_10+":0.0},"link":"","children":[],"checksum":"c542f9b251780336"},{"name":"broker","type":"Folder","attributes":{},"link":"","children":[{"name":"IBrokerAdapter.ts","type":"File","attributes":{"loc":1.0,"indentation_level_0+":1.0,"indentation_level_1+":0.0,"indentation_level_2+":0.0,"indentation_level_3+":0.0,"indentation_level_4+":0.0,"indentation_level_5+":0.0,"indentation_level_6+":0.0,"indentation_level_7+":0.0,"indentation_level_8+":0.0,"indentation_level_9+":0.0,"indentation_level_10+":0.0},"link":"","children":[],"checksum":"b9f9ea3737f6c937"},{"name":"alpaca.adapter.ts","type":"File","attributes":{"loc":486.0,"indentation_level_0+":409.0,"indentation_level_1+":401.0,"indentation_level_2+":401.0,"indentation_level_3+":348.0,"indentation_level_4+":345.0,"indentation_level_5+":182.0,"indentation_level_6+":182.0,"indentation_level_7+":63.0,"indentation_level_8+":63.0,"indentation_level_9+":17.0,"indentation_level_10+":17.0},"link":"","children":[],"checksum":"e50302b0d3ddba3e"}]},{"name":"trading.engine.ts","type":"File","attributes":{"loc":107.0,"indentation_level_0+":91.0,"indentation_level_1+":60.0,"indentation_level_2+":45.0,"indentation_level_3+":10.0,"indentation_level_4+":10.0,"indentation_level_5+":0.0,"indentation_level_6+":0.0,"indentation_level_7+":0.0,"indentation_level_8+":0.0,"indentation_level_9+":0.0,"indentation_level_10+":0.0},"link":"","children":[],"checksum":"b04d74639a20240d"}]},{"name":"app.module.ts","type":"File","attributes":{"loc":34.0,"indentation_level_0+":33.0,"indentation_level_1+":16.0,"indentation_level_2+":12.0,"indentation_level_3+":0.0,"indentation_level_4+":0.0,"indentation_level_5+":0.0,"indentation_level_6+":0.0,"indentation_level_7+":0.0,"indentation_level_8+":0.0,"indentation_level_9+":0.0,"indentation_level_10+":0.0},"link":"","children":[],"checksum":"d2018a20d8b15c0a"},{"name":"common","type":"Folder","attributes":{},"link":"","children":[{"name":"interceptors","type":"Folder","attributes":{},"link":"","children":[{"name":"logging.interceptor.ts","type":"File","attributes":{"loc":41.0,"indentation_level_0+":36.0,"indentation_level_1+":26.0,"indentation_level_2+":15.0,"indentation_level_3+":10.0,"indentation_level_4+":8.0,"indentation_level_5+":4.0,"indentation_level_6+":0.0,"indentation_level_7+":0.0,"indentation_level_8+":0.0,"indentation_level_9+":0.0,"indentation_level_10+":0.0},"link":"","children":[],"checksum":"4803994f484b94ca"}]},{"name":"pipes","type":"Folder","attributes":{},"link":"","children":[{"name":"zod-validation.pipe.ts","type":"File","attributes":{"loc":14.0,"indentation_level_0+":12.0,"indentation_level_1+":8.0,"indentation_level_2+":5.0,"indentation_level_3+":1.0,"indentation_level_4+":0.0,"indentation_level_5+":0.0,"indentation_level_6+":0.0,"indentation_level_7+":0.0,"indentation_level_8+":0.0,"indentation_level_9+":0.0,"indentation_level_10+":0.0},"link":"","children":[],"checksum":"d2a8b39da44de71e"}]}]},{"name":"api-keys","type":"Folder","attributes":{},"link":"","children":[{"name":"api-keys.service.ts","type":"File","attributes":{"loc":43.0,"indentation_level_0+":36.0,"indentation_level_1+":29.0,"indentation_level_2+":19.0,"indentation_level_3+":0.0,"indentation_level_4+":0.0,"indentation_level_5+":0.0,"indentation_level_6+":0.0,"indentation_level_7+":0.0,"indentation_level_8+":0.0,"indentation_level_9+":0.0,"indentation_level_10+":0.0},"link":"","children":[],"checksum":"ab5922fdaaaff466"},{"name":"api-keys.module.ts","type":"File","attributes":{"loc":13.0,"indentation_level_0+":12.0,"indentation_level_1+":3.0,"indentation_level_2+":0.0,"indentation_level_3+":0.0,"indentation_level_4+":0.0,"indentation_level_5+":0.0,"indentation_level_6+":0.0,"indentation_level_7+":0.0,"indentation_level_8+":0.0,"indentation_level_9+":0.0,"indentation_level_10+":0.0},"link":"","children":[],"checksum":"a2eb288491b77f15"},{"name":"api-keys.repository.ts","type":"File","attributes":{"loc":23.0,"indentation_level_0+":19.0,"indentation_level_1+":14.0,"indentation_level_2+":7.0,"indentation_level_3+":3.0,"indentation_level_4+":0.0,"indentation_level_5+":0.0,"indentation_level_6+":0.0,"indentation_level_7+":0.0,"indentation_level_8+":0.0,"indentation_level_9+":0.0,"indentation_level_10+":0.0},"link":"","children":[],"checksum":"e1c88c85dcd894d5"},{"name":"api-keys.controller.ts","type":"File","attributes":{"loc":45.0,"indentation_level_0+":40.0,"indentation_level_1+":26.0,"indentation_level_2+":4.0,"indentation_level_3+":0.0,"indentation_level_4+":0.0,"indentation_level_5+":0.0,"indentation_level_6+":0.0,"indentation_level_7+":0.0,"indentation_level_8+":0.0,"indentation_level_9+":0.0,"indentation_level_10+":0.0},"link":"","children":[],"checksum":"cad940079534aa9d"}]},{"name":"trade-logs","type":"Folder","attributes":{},"link":"","children":[{"name":"trade-logs.repository.ts","type":"File","attributes":{"loc":67.0,"indentation_level_0+":60.0,"indentation_level_1+":52.0,"indentation_level_2+":36.0,"indentation_level_3+":27.0,"indentation_level_4+":4.0,"indentation_level_5+":0.0,"indentation_level_6+":0.0,"indentation_level_7+":0.0,"indentation_level_8+":0.0,"indentation_level_9+":0.0,"indentation_level_10+":0.0},"link":"","children":[],"checksum":"7f60582b8da785c4"},{"name":"trade-logs.module.ts","type":"File","attributes":{"loc":8.0,"indentation_level_0+":7.0,"indentation_level_1+":2.0,"indentation_level_2+":0.0,"indentation_level_3+":0.0,"indentation_level_4+":0.0,"indentation_level_5+":0.0,"indentation_level_6+":0.0,"indentation_level_7+":0.0,"indentation_level_8+":0.0,"indentation_level_9+":0.0,"indentation_level_10+":0.0},"link":"","children":[],"checksum":"84ea90af0b3e21f6"}]},{"name":"blueprints","type":"Folder","attributes":{},"link":"","children":[{"name":"blueprints.controller.ts","type":"File","attributes":{"loc":130.0,"indentation_level_0+":118.0,"indentation_level_1+":104.0,"indentation_level_2+":42.0,"indentation_level_3+":0.0,"indentation_level_4+":0.0,"indentation_level_5+":0.0,"indentation_level_6+":0.0,"indentation_level_7+":0.0,"indentation_level_8+":0.0,"indentation_level_9+":0.0,"indentation_level_10+":0.0},"link":"","children":[],"checksum":"6c83082078a98ce9"},{"name":"blueprints.repository.ts","type":"File","attributes":{"loc":57.0,"indentation_level_0+":47.0,"indentation_level_1+":41.0,"indentation_level_2+":22.0,"indentation_level_3+":9.0,"indentation_level_4+":0.0,"indentation_level_5+":0.0,"indentation_level_6+":0.0,"indentation_level_7+":0.0,"indentation_level_8+":0.0,"indentation_level_9+":0.0,"indentation_level_10+":0.0},"link":"","children":[],"checksum":"241b20d845fb28aa"},{"name":"blueprints.module.ts","type":"File","attributes":{"loc":13.0,"indentation_level_0+":12.0,"indentation_level_1+":4.0,"indentation_level_2+":0.0,"indentation_level_3+":0.0,"indentation_level_4+":0.0,"indentation_level_5+":0.0,"indentation_level_6+":0.0,"indentation_level_7+":0.0,"indentation_level_8+":0.0,"indentation_level_9+":0.0,"indentation_level_10+":0.0},"link":"","children":[],"checksum":"b33fe51c17ea02cf"},{"name":"blueprints.service.ts","type":"File","attributes":{"loc":211.0,"indentation_level_0+":179.0,"indentation_level_1+":169.0,"indentation_level_2+":142.0,"indentation_level_3+":53.0,"indentation_level_4+":21.0,"indentation_level_5+":12.0,"indentation_level_6+":0.0,"indentation_level_7+":0.0,"indentation_level_8+":0.0,"indentation_level_9+":0.0,"indentation_level_10+":0.0},"link":"","children":[],"checksum":"428a9c6413d93a68"}]},{"name":"subscriptions","type":"Folder","attributes":{},"link":"","children":[{"name":"subscriptions.repository.ts","type":"File","attributes":{"loc":57.0,"indentation_level_0+":49.0,"indentation_level_1+":44.0,"indentation_level_2+":29.0,"indentation_level_3+":16.0,"indentation_level_4+":4.0,"indentation_level_5+":0.0,"indentation_level_6+":0.0,"indentation_level_7+":0.0,"indentation_level_8+":0.0,"indentation_level_9+":0.0,"indentation_level_10+":0.0},"link":"","children":[],"checksum":"33b3b7acbbf6b9d8"},{"name":"subscriptions.controller.ts","type":"File","attributes":{"loc":80.0,"indentation_level_0+":73.0,"indentation_level_1+":57.0,"indentation_level_2+":18.0,"indentation_level_3+":4.0,"indentation_level_4+":0.0,"indentation_level_5+":0.0,"indentation_level_6+":0.0,"indentation_level_7+":0.0,"indentation_level_8+":0.0,"indentation_level_9+":0.0,"indentation_level_10+":0.0},"link":"","children":[],"checksum":"bd8beeb42b16459f"},{"name":"subscriptions.module.ts","type":"File","attributes":{"loc":14.0,"indentation_level_0+":13.0,"indentation_level_1+":4.0,"indentation_level_2+":0.0,"indentation_level_3+":0.0,"indentation_level_4+":0.0,"indentation_level_5+":0.0,"indentation_level_6+":0.0,"indentation_level_7+":0.0,"indentation_level_8+":0.0,"indentation_level_9+":0.0,"indentation_level_10+":0.0},"link":"","children":[],"checksum":"bf9a0b1bc062893d"},{"name":"subscriptions.service.ts","type":"File","attributes":{"loc":66.0,"indentation_level_0+":53.0,"indentation_level_1+":44.0,"indentation_level_2+":30.0,"indentation_level_3+":0.0,"indentation_level_4+":0.0,"indentation_level_5+":0.0,"indentation_level_6+":0.0,"indentation_level_7+":0.0,"indentation_level_8+":0.0,"indentation_level_9+":0.0,"indentation_level_10+":0.0},"link":"","children":[],"checksum":"b4c61295f30cee9a"}]},{"name":"encryption","type":"Folder","attributes":{},"link":"","children":[{"name":"encryption.service.ts","type":"File","attributes":{"loc":47.0,"indentation_level_0+":36.0,"indentation_level_1+":31.0,"indentation_level_2+":23.0,"indentation_level_3+":3.0,"indentation_level_4+":0.0,"indentation_level_5+":0.0,"indentation_level_6+":0.0,"indentation_level_7+":0.0,"indentation_level_8+":0.0,"indentation_level_9+":0.0,"indentation_level_10+":0.0},"link":"","children":[],"checksum":"80bb525ee3465a28"},{"name":"encryption.module.ts","type":"File","attributes":{"loc":8.0,"indentation_level_0+":7.0,"indentation_level_1+":2.0,"indentation_level_2+":0.0,"indentation_level_3+":0.0,"indentation_level_4+":0.0,"indentation_level_5+":0.0,"indentation_level_6+":0.0,"indentation_level_7+":0.0,"indentation_level_8+":0.0,"indentation_level_9+":0.0,"indentation_level_10+":0.0},"link":"","children":[],"checksum":"1ea10c0200366137"}]},{"name":"main.ts","type":"File","attributes":{"loc":18.0,"indentation_level_0+":14.0,"indentation_level_1+":9.0,"indentation_level_2+":2.0,"indentation_level_3+":0.0,"indentation_level_4+":0.0,"indentation_level_5+":0.0,"indentation_level_6+":0.0,"indentation_level_7+":0.0,"indentation_level_8+":0.0,"indentation_level_9+":0.0,"indentation_level_10+":0.0},"link":"","children":[],"checksum":"026010e9e5fb5167"}]}]}]},{"name":"packages","type":"Folder","attributes":{},"link":"","children":[{"name":"types","type":"Folder","attributes":{},"link":"","children":[{"name":"src","type":"Folder","attributes":{},"link":"","children":[{"name":"schemas","type":"Folder","attributes":{},"link":"","children":[{"name":"blueprint.schema.ts","type":"File","attributes":{"loc":56.0,"indentation_level_0+":48.0,"indentation_level_1+":28.0,"indentation_level_2+":5.0,"indentation_level_3+":2.0,"indentation_level_4+":0.0,"indentation_level_5+":0.0,"indentation_level_6+":0.0,"indentation_level_7+":0.0,"indentation_level_8+":0.0,"indentation_level_9+":0.0,"indentation_level_10+":0.0},"link":"","children":[],"checksum":"f211e3f3d81b835d"},{"name":"auth.schema.ts","type":"File","attributes":{"loc":34.0,"indentation_level_0+":29.0,"indentation_level_1+":15.0,"indentation_level_2+":6.0,"indentation_level_3+":0.0,"indentation_level_4+":0.0,"indentation_level_5+":0.0,"indentation_level_6+":0.0,"indentation_level_7+":0.0,"indentation_level_8+":0.0,"indentation_level_9+":0.0,"indentation_level_10+":0.0},"link":"","children":[],"checksum":"c02602c7023646b3"},{"name":"backtest.schema.ts","type":"File","attributes":{"loc":47.0,"indentation_level_0+":42.0,"indentation_level_1+":26.0,"indentation_level_2+":0.0,"indentation_level_3+":0.0,"indentation_level_4+":0.0,"indentation_level_5+":0.0,"indentation_level_6+":0.0,"indentation_level_7+":0.0,"indentation_level_8+":0.0,"indentation_level_9+":0.0,"indentation_level_10+":0.0},"link":"","children":[],"checksum":"3940ac84e61d4e05"},{"name":"api-key.schema.ts","type":"File","attributes":{"loc":16.0,"indentation_level_0+":12.0,"indentation_level_1+":3.0,"indentation_level_2+":0.0,"indentation_level_3+":0.0,"indentation_level_4+":0.0,"indentation_level_5+":0.0,"indentation_level_6+":0.0,"indentation_level_7+":0.0,"indentation_level_8+":0.0,"indentation_level_9+":0.0,"indentation_level_10+":0.0},"link":"","children":[],"checksum":"537f9068a0e4a2fd"},{"name":"trade-log.schema.ts","type":"File","attributes":{"loc":18.0,"indentation_level_0+":15.0,"indentation_level_1+":9.0,"indentation_level_2+":0.0,"indentation_level_3+":0.0,"indentation_level_4+":0.0,"indentation_level_5+":0.0,"indentation_level_6+":0.0,"indentation_level_7+":0.0,"indentation_level_8+":0.0,"indentation_level_9+":0.0,"indentation_level_10+":0.0},"link":"","children":[],"checksum":"97a1f9362c45f4a2"},{"name":"subscription.schema.ts","type":"File","attributes":{"loc":40.0,"indentation_level_0+":34.0,"indentation_level_1+":17.0,"indentation_level_2+":0.0,"indentation_level_3+":0.0,"indentation_level_4+":0.0,"indentation_level_5+":0.0,"indentation_level_6+":0.0,"indentation_level_7+":0.0,"indentation_level_8+":0.0,"indentation_level_9+":0.0,"indentation_level_10+":0.0},"link":"","children":[],"checksum":"62c1708baf024b72"},{"name":"market-data.schema.ts","type":"File","attributes":{"loc":26.0,"indentation_level_0+":21.0,"indentation_level_1+":10.0,"indentation_level_2+":0.0,"indentation_level_3+":0.0,"indentation_level_4+":0.0,"indentation_level_5+":0.0,"indentation_level_6+":0.0,"indentation_level_7+":0.0,"indentation_level_8+":0.0,"indentation_level_9+":0.0,"indentation_level_10+":0.0},"link":"","children":[],"checksum":"e2430795a4d2b0f9"}]},{"name":"index.ts","type":"File","attributes":{"loc":15.0,"indentation_level_0+":13.0,"indentation_level_1+":0.0,"indentation_level_2+":0.0,"indentation_level_3+":0.0,"indentation_level_4+":0.0,"indentation_level_5+":0.0,"indentation_level_6+":0.0,"indentation_level_7+":0.0,"indentation_level_8+":0.0,"indentation_level_9+":0.0,"indentation_level_10+":0.0},"link":"","children":[],"checksum":"b4660ab9af34653b"},{"name":"interfaces","type":"Folder","attributes":{},"link":"","children":[{"name":"IBrokerAdapter.ts","type":"File","attributes":{"loc":46.0,"indentation_level_0+":42.0,"indentation_level_1+":32.0,"indentation_level_2+":3.0,"indentation_level_3+":0.0,"indentation_level_4+":0.0,"indentation_level_5+":0.0,"indentation_level_6+":0.0,"indentation_level_7+":0.0,"indentation_level_8+":0.0,"indentation_level_9+":0.0,"indentation_level_10+":0.0},"link":"","children":[],"checksum":"cb7b027c03be3540"},{"name":"index.ts","type":"File","attributes":{"loc":58.0,"indentation_level_0+":51.0,"indentation_level_1+":37.0,"indentation_level_2+":0.0,"indentation_level_3+":0.0,"indentation_level_4+":0.0,"indentation_level_5+":0.0,"indentation_level_6+":0.0,"indentation_level_7+":0.0,"indentation_level_8+":0.0,"indentation_level_9+":0.0,"indentation_level_10+":0.0},"link":"","children":[],"checksum":"fea5f7cb85a3afa8"}]},{"name":"enums.ts","type":"File","attributes":{"loc":24.0,"indentation_level_0+":21.0,"indentation_level_1+":13.0,"indentation_level_2+":0.0,"indentation_level_3+":0.0,"indentation_level_4+":0.0,"indentation_level_5+":0.0,"indentation_level_6+":0.0,"indentation_level_7+":0.0,"indentation_level_8+":0.0,"indentation_level_9+":0.0,"indentation_level_10+":0.0},"link":"","children":[],"checksum":"62300d5c71af20f5"}]}]}]}]}],"apiVersion":"1.5","edges":[],"attributeTypes":{},"attributeDescriptors":{"indentation_level_0+":{"title":"Statements with indentation level greater or equal 0","description":"Statements with indentation level greater or equal 0","hintLowValue":"","hintHighValue":"","link":"https://codecharta.com/docs/parser/raw-text","direction":-1,"analyzers":["rawtextParser"]},"indentation_level_1+":{"title":"Statements with indentation level greater or equal 1","description":"Statements with indentation level greater or equal 1","hintLowValue":"","hintHighValue":"","link":"https://codecharta.com/docs/parser/raw-text","direction":-1,"analyzers":["rawtextParser"]},"indentation_level_2+":{"title":"Statements with indentation level greater or equal 2","description":"Statements with indentation level greater or equal 2","hintLowValue":"","hintHighValue":"","link":"https://codecharta.com/docs/parser/raw-text","direction":-1,"analyzers":["rawtextParser"]},"indentation_level_3+":{"title":"Statements with indentation level greater or equal 3","description":"Statements with indentation level greater or equal 3","hintLowValue":"","hintHighValue":"","link":"https://codecharta.com/docs/parser/raw-text","direction":-1,"analyzers":["rawtextParser"]},"indentation_level_4+":{"title":"Statements with indentation level greater or equal 4","description":"Statements with indentation level greater or equal 4","hintLowValue":"","hintHighValue":"","link":"https://codecharta.com/docs/parser/raw-text","direction":-1,"analyzers":["rawtextParser"]},"indentation_level_5+":{"title":"Statements with indentation level greater or equal 5","description":"Statements with indentation level greater or equal 5","hintLowValue":"","hintHighValue":"","link":"https://codecharta.com/docs/parser/raw-text","direction":-1,"analyzers":["rawtextParser"]},"indentation_level_6+":{"title":"Statements with indentation level greater or equal 6","description":"Statements with indentation level greater or equal 6","hintLowValue":"","hintHighValue":"","link":"https://codecharta.com/docs/parser/raw-text","direction":-1,"analyzers":["rawtextParser"]},"indentation_level_7+":{"title":"Statements with indentation level greater or equal 7","description":"Statements with indentation level greater or equal 7","hintLowValue":"","hintHighValue":"","link":"https://codecharta.com/docs/parser/raw-text","direction":-1,"analyzers":["rawtextParser"]},"indentation_level_8+":{"title":"Statements with indentation level greater or equal 8","description":"Statements with indentation level greater or equal 8","hintLowValue":"","hintHighValue":"","link":"https://codecharta.com/docs/parser/raw-text","direction":-1,"analyzers":["rawtextParser"]},"indentation_level_9+":{"title":"Statements with indentation level greater or equal 9","description":"Statements with indentation level greater or equal 9","hintLowValue":"","hintHighValue":"","link":"https://codecharta.com/docs/parser/raw-text","direction":-1,"analyzers":["rawtextParser"]},"indentation_level_10+":{"title":"Statements with indentation level greater or equal 10","description":"Statements with indentation level greater or equal 10","hintLowValue":"","hintHighValue":"","link":"https://codecharta.com/docs/parser/raw-text","direction":-1,"analyzers":["rawtextParser"]},"loc":{"title":"Lines of Code","description":"Lines of code including empty lines and comments","hintLowValue":"","hintHighValue":"","link":"https://codecharta.com/docs/parser/raw-text","direction":-1,"analyzers":["rawtextParser"]}},"blacklist":[]},"checksum":"a807b5065055014b80773a631b7631db"}